comicon/__init__.py
comicon/api.py
comicon/base.py
comicon/cirtools.py
comicon/common/__init__.py
comicon/common/cbz.py
comicon/common/cir.py
comicon/common/epub.py
comicon/common/pdf.py
comicon/errors.py
comicon/image.py
comicon/inputs/__init__.py
comicon/inputs/cbz.py
comicon/inputs/cir.py
comicon/inputs/epub.py
comicon/inputs/pdf.py
comicon/outputs/__init__.py
comicon/outputs/cbz.py
comicon/outputs/cir.py
comicon/outputs/epub.py
comicon/outputs/mobi.py
comicon/outputs/pdf.py
comicon-1.5.0.dist-info/LICENSE
comicon-1.5.0.dist-info/METADATA
comicon-1.5.0.dist-info/WHEEL
comicon-1.5.0.dist-info/RECORD
