Metadata-Version: 2.3
Name: comicon
Version: 1.5.0
Summary: A simple comic conversion library between CBZ/EPUB/MOBI/PDF
License: AGPL-3.0-only
Keywords: converter,comic,cbz,epub,pdf,mobi
Author: potatoeggy
Author-email: eggyrules@gmail.com
Requires-Python: >=3.10
Classifier: License :: OSI Approved :: GNU Affero General Public License v3
Classifier: Programming Language :: Python :: 3
Classifier: Programming Language :: Python :: 3.10
Classifier: Programming Language :: Python :: 3.11
Classifier: Programming Language :: Python :: 3.12
Classifier: Programming Language :: Python :: 3.13
Requires-Dist: ebooklib (>=0.18,<0.19)
Requires-Dist: lxml (>=5.4.0,<6.0.0)
Requires-Dist: pillow (>=11.2.1,<12.0.0)
Requires-Dist: pypdf[image] (>=5.4.0,<6.0.0)
Requires-Dist: python-slugify (>=8.0.4,<9.0.0)
Project-URL: Documentation, https://github.com/potatoeggy/comicon
Project-URL: Repository, https://github.com/potatoeggy/comicon
